{"data":{"allNavItemsYaml":{"edges":[{"node":{"title":"Dataset","pages":[{"title":null,"path":"/dataset"}],"hasDivider":null}},{"node":{"title":"Visualizations","pages":[{"title":null,"path":"/visualizations"}],"hasDivider":null}},{"node":{"title":"Publications","pages":[{"title":null,"path":"/publications"}],"hasDivider":null}},{"node":{"title":"Team","pages":[{"title":null,"path":"/team"}],"hasDivider":null}},{"node":{"title":"Contribute","pages":[{"title":null,"path":"/contribute"}],"hasDivider":null}}]}}}